promptpalette/__init__.py
promptpalette/_client.py
promptpalette/_composer.py
promptpalette/src/kb/__init__.py
promptpalette/src/kb/examples/active-prompting-cot.md
promptpalette/src/kb/examples/art-automatic-multi-step-reasoning-prompting.md
promptpalette/src/kb/examples/chain-of-code-prompting.md
promptpalette/src/kb/examples/chain-of-knowledge-prompting.md
promptpalette/src/kb/examples/chain-of-note-prompting.md
promptpalette/src/kb/examples/chain-of-symbol-prompting.md
promptpalette/src/kb/examples/chain-of-table-prompting.md
promptpalette/src/kb/examples/chain-of-verification-prompting.md
promptpalette/src/kb/examples/contrastive-chain-of-thought-prompting.md
promptpalette/src/kb/examples/cot-prompting.md
promptpalette/src/kb/examples/guided-tree-of-thought-prompting.md
promptpalette/src/kb/examples/language-model-few-shot-learners.md
promptpalette/src/kb/examples/llm-emotional-stimuli-prompting.md
promptpalette/src/kb/examples/llm-human-level-prompt-engineers.md
promptpalette/src/kb/examples/program-of-thoughts-prompting.md
promptpalette/src/kb/examples/react-prompting.md
promptpalette/src/kb/examples/reasoning-via-abstraction-prompting.md
promptpalette/src/kb/examples/rephrase-and-response-prompting.md
promptpalette/src/kb/examples/scratchpad-prompting.md
promptpalette/src/kb/examples/self-consistency-cot-prompting.md
promptpalette/src/kb/examples/structured-chain-of-thought-code-generation-prompting.md
promptpalette/src/kb/examples/tree-of-thought-problem-solving-prompting.md
promptpalette/src/kb/examples/zero-shot-chain-of-thought-reasoning-prompting.md
promptpalette/src/kb/kb.py
promptpalette/src/kb/knowledgebase/active-prompting-cot.md
promptpalette/src/kb/knowledgebase/art-automatic-multi-step-reasoning-prompting.md
promptpalette/src/kb/knowledgebase/chain-of-code-prompting.md
promptpalette/src/kb/knowledgebase/chain-of-knowledge-prompting.md
promptpalette/src/kb/knowledgebase/chain-of-note-prompting.md
promptpalette-0.4.0.dist-info/METADATA
promptpalette-0.4.0.dist-info/WHEEL
promptpalette-0.4.0.dist-info/RECORD
