Metadata-Version: 2.1
Name: promptpalette
Version: 0.4.0
Summary: 
Author: vatsalsaglani
Author-email: saglanivatsal@gmail.com
Requires-Python: >=3.10,<4.0
Classifier: Programming Language :: Python :: 3
Classifier: Programming Language :: Python :: 3.10
Classifier: Programming Language :: Python :: 3.11
Classifier: Programming Language :: Python :: 3.12
Requires-Dist: anthropic[bedrock] (>=0.34.0,<0.35.0)
Requires-Dist: claudetools (>=1.0.2,<2.0.0)
Requires-Dist: groq (>=0.9.0,<0.10.0)
Requires-Dist: httpx (>=0.27.0,<0.28.0)
Requires-Dist: openai[azure] (>=1.41.0,<2.0.0)
Requires-Dist: pydantic (>=2.8.2,<3.0.0)
Requires-Dist: tiktoken (>=0.7.0,<0.8.0)
Requires-Dist: tqdm (>=4.66.5,<5.0.0)
Requires-Dist: transformers (>=4.44.0,<5.0.0)
